mo_bayes_opt/__init__.py
mo_bayes_opt/acquisition/__init__.py
mo_bayes_opt/acquisition/optimize.py
mo_bayes_opt/core/__init__.py
mo_bayes_opt/core/bo.py
mo_bayes_opt/models/__init__.py
mo_bayes_opt/models/gp.py
mo_bayes_opt/utils/__init__.py
mo_bayes_opt/utils/logger.py
mo_bayes_opt/utils/visualization.py
mo_bayes_opt-0.1.0.dist-info/METADATA
mo_bayes_opt-0.1.0.dist-info/WHEEL
mo_bayes_opt-0.1.0.dist-info/top_level.txt
mo_bayes_opt-0.1.0.dist-info/RECORD
