Metadata-Version: 2.4
Name: mo_bayes_opt
Version: 0.1.0
Summary: Multi-Objective Bayesian Optimization with Gaussian Processes and adaptive noise
Home-page: https://github.com/zhazhajust/mo_bayes_opt
Author: Jie Cai
Author-email: zhazhajust@gmail.com
License: MIT
Classifier: Development Status :: 4 - Beta
Classifier: Intended Audience :: Science/Research
Classifier: License :: OSI Approved :: MIT License
Classifier: Programming Language :: Python :: 3
Classifier: Topic :: Scientific/Engineering :: Artificial Intelligence
Requires-Python: >=3.7
Requires-Dist: torch>=1.10
Requires-Dist: gpytorch>=1.8
Requires-Dist: botorch>=0.8
Requires-Dist: pandas>=1.3
Requires-Dist: matplotlib>=3.4
Requires-Dist: tqdm>=4.60
Provides-Extra: dev
Requires-Dist: pytest; extra == "dev"
Requires-Dist: black; extra == "dev"
Requires-Dist: flake8; extra == "dev"
Requires-Dist: jupyter; extra == "dev"
Dynamic: author
Dynamic: author-email
Dynamic: classifier
Dynamic: description
Dynamic: description-content-type
Dynamic: home-page
Dynamic: license
Dynamic: provides-extra
Dynamic: requires-dist
Dynamic: requires-python
Dynamic: summary
